Workbook

Sheet PENJ-ALL-SALES
B4: TOTAL ALL SALES
B5: PRODUK | C5: CASH | E5: KREDIT / TEMPO | G5: TOTAL
C6: QTY | D6: NOM | E6: QTY | F6: NOM | G6: QTY | H6: NOMINAL
B7: FB200 | C7: 3 | D7: 347400 | G7: =SUM(C7+E7) -> 3 | H7: =SUM(D7+F7) -> 347400
B8: FB400 | C8: =SUM(C17+C27+C37) -> 327 | D8: =SUM(D17+D27+D37) -> 36997600 | E8: =SUM(E17+E27+E37) -> 561 | F8: =SUM(F17+F27+F37) -> 63468800 | G8: =SUM(C8+E8) -> 888 | H8: =SUM(D8+F8) -> 100466400
B9: FB800 | C9: =SUM(C18+C28+C38) -> 693 | D9: =SUM(D18+D28+D38) -> 147564300 | E9: =SUM(E18+E28+E38) -> 1121 | F9: =SUM(F18+F28+F38) -> 241127100 | G9: =SUM(C9+E9) -> 1814 | H9: =SUM(D9+F9) -> 388691400
C11: =SUM(C7:C9) -> 1023 | D11: =SUM(D7:D9) -> 184909300 | E11: =SUM(E7:E9) -> 1682 | F11: =SUM(F7:F9) -> 304595900 | G11: =SUM(G7:G9) -> 2705 | H11: =SUM(H7:H9) -> 489505200
B13: JOSSY
B14: PRODUK | C14: CASH | E14: KREDIT / TEMPO | G14: TOTAL
C15: QTY | D15: NOM | E15: QTY | F15: NOM | G15: QTY | H15: NOMINAL
B16: FB200 | C16: 3 | D16: 347400 | F16: 3 | G16: =SUM(C16+E16) -> 3 | H16: =SUM(D16+F16) -> 347403
B17: FB400 | C17: 142 | D17: 16051200 | E17: 152 | F17: 17193600 | G17: =SUM(C17+E17) -> 294 | H17: =SUM(D17+F17) -> 33244800
B18: FB800 | C18: 354 | D18: 75545400 | E18: 393 | F18: 84534300 | G18: =SUM(C18+E18) -> 747 | H18: =SUM(D18+F18) -> 160079700
C20: =SUM(C16:C18) -> 499 | D20: =SUM(D16:D18) -> 91944000 | E20: =SUM(E16:E18) -> 545 | F20: =SUM(F16:F18) -> 101727903 | G20: =SUM(G16:G18) -> 1044 | H20: =SUM(H16:H19) -> 193671903
B23: RAJU
B24: PRODUK | C24: CASH | E24: KREDIT / TEMPO | G24: TOTAL
C25: QTY | D25: NOM | E25: QTY | F25: NOM | G25: QTY | H25: NOMINAL
B26: FB200 | H26: =SUM(D26+F26) -> 0
B27: FB400 | C27: 7 | D27: 792800 | E27: 265 | F27: 30001600 | G27: =SUM(C27+E27) -> 272 | H27: =SUM(D27+F27) -> 30794400
B28: FB800 | C28: 125 | D28: 26287500 | E28: 381 | F28: 81953100 | G28: =SUM(C28+E28) -> 506 | H28: =SUM(D28+F28) -> 108240600
C30: =SUM(C27:C28) -> 132 | D30: =SUM(D26:D28) -> 27080300 | E30: =SUM(E26:E28) -> 646 | F30: =SUM(F26:F28) -> 111954700 | G30: =SUM(G26:G28) -> 778 | H30: =SUM(H26:H29) -> 139035000
B33: HAFID
C34: CASH | E34: KREDIT / TEMPO | G34: TOTAL
C35: QTY | D35: NOM | E35: QTY | F35: NOM | G35: QTY | H35: NOMINAL
B36: FB200
B37: FB400 | C37: 178 | D37: 20153600 | E37: 144 | F37: 16273600 | G37: =SUM(C37+E37) -> 322 | H37: =SUM(D37+F37) -> 36427200
B38: FB800 | C38: 214 | D38: 45731400 | E38: 347 | F38: 74639700 | G38: =SUM(C38+E38) -> 561 | H38: =SUM(D38+F38) -> 120371100
C40: =SUM(C37:C38) -> 392 | D40: =SUM(D36:D38) -> 65885000 | E40: =SUM(E36:E38) -> 491 | F40: =SUM(F36:F38) -> 90913300 | G40: =SUM(G36:G38) -> 883 | H40: =SUM(H36:H39) -> 156798300

Sheet PROFIT ALL SALES
B2: PROFIT MEI 2026
B4: PENJUALAN ALL SALES
B5: PRODUK | C5: PENJUALAN CASH | E5: PENJUALAN KREDIT / TEMPO | G5: TOTAL PENJUALAN
C6: QTY | D6: NOM | E6: QTY | F6: NOM | G6: QTY | H6: NOMINAL
B7: FB200 | C7: =SUM('PENJ-ALL-SALES'!C7) -> 3 | D7: =SUM('PENJ-ALL-SALES'!D7) -> 347400 | E7: =SUM('PENJ-ALL-SALES'!E7) -> 0 | F7: =SUM('PENJ-ALL-SALES'!F7) -> 0 | G7: =SUM(C7+E7) -> 3 | H7: =SUM(D7+F7) -> 347400
B8: FB400 | C8: =SUM('PENJ-ALL-SALES'!C8) -> 327 | D8: =SUM('PENJ-ALL-SALES'!D8) -> 36997600 | E8: =SUM('PENJ-ALL-SALES'!E8) -> 561 | F8: =SUM('PENJ-ALL-SALES'!F8) -> 63468800 | G8: =SUM(C8+E8) -> 888 | H8: =SUM(D8+F8) -> 100466400
B9: FB800 | C9: =SUM('PENJ-ALL-SALES'!C9) -> 693 | D9: =SUM('PENJ-ALL-SALES'!D9) -> 147564300 | E9: =SUM('PENJ-ALL-SALES'!E9) -> 1121 | F9: =SUM('PENJ-ALL-SALES'!F9) -> 241127100 | G9: =SUM(C9+E9) -> 1814 | H9: =SUM(D9+F9) -> 388691400
C11: 1023 | D11: 184909300 | E11: =SUM(E7:E9) -> 1682 | F11: =SUM(F7:F9) -> 304595900 | G11: =SUM(G7:G9) -> 2705 | H11: =SUM(H7:H9) -> 489505200
B14: PROFIT CASH ALL SALES
B15: PRODUK | C15: HARGA BELI | D15: QTY TERJUAL CASH | E15: NOM PEMBELIAN | F15: NOMINAL PENJUALAN | G15: PROFIT CASH
B16: FB200 | C16: 110500 | D16: =SUM(C7) -> 3 | E16: =SUM(C16*D16) -> 331500 | F16: =SUM(D7) -> 347400 | H16: =SUM(F16-E16) -> 15900
B17: FB400 | C17: 107500 | D17: =SUM(C8) -> 327 | E17: =SUM(C17*D17) -> 35152500 | F17: =SUM(D8) -> 36997600 | H17: =SUM(F17-E17) -> 1845100
B18: FB800 | C18: 201900 | D18: =SUM(C9) -> 693 | E18: =SUM(C18*D18) -> 139916700 | F18: =SUM(D9) -> 147564300 | H18: =SUM(F18-E18) -> 7647600
H20: =SUM(H16:H18) -> 9508600
B22: PROFIT TEMPO ALL SALES
B23: PRODUK | C23: HARGA BELI | D23: QTY TERJUAL TEMPO | E23: NOM PEMBELIAN | F23: NOMINAL PENJUALAN | G23: PROFIT TEMPO
B24: FB200 | C24: 110500 | D24: =SUM(E7) -> 0 | E24: =SUM(C24*D24) -> 0 | F24: =SUM(F7) -> 0 | H24: =SUM(F24-E24) -> 0
B25: FB400 | C25: 107500 | D25: =SUM(E8) -> 561 | E25: =SUM(C25*D25) -> 60307500 | F25: =SUM(F8) -> 63468800 | H25: =SUM(F25-E25) -> 3161300
B26: FB800 | C26: 201900 | D26: =SUM(E9) -> 1121 | E26: =SUM(C26*D26) -> 226329900 | F26: =SUM(F9) -> 241127100 | H26: =SUM(F26-E26) -> 14797200
H28: =SUM(H24:H26) -> 17958500

Sheet JOSSY
B1: penjualan Jossy
B3: Sales | C3: Tanggal | D3: Customer | E3: Produk | F3: QTY Penjualan ( krat) | G3: Harga jual | H3: Nominal | I3: Jenis Pembayaran
B4: JOSSY | C4: 46143.314 | D4: MEVA CELL | E4: FITRI BOTOL 400ML | F4: 1 | G4: 112800 | H4: 112800 | I4: Kredit
B5: JOSSY | C5: 46143.314 | D5: MEVA CELL | E5: FITRI BOTOL 800ML | F5: 1 | G5: 215100 | H5: 215100 | I5: Kredit
B6: JOSSY | C6: 46143.316 | D6: TOKO AMAN MAKMUR | E6: FITRI BOTOL 800ML | F6: 2 | G6: 215100 | H6: 430200 | I6: Kredit
B7: JOSSY | C7: 46143.317 | D7: SUMBER BERKAH | E7: FITRI BOTOL 400ML | F7: 1 | G7: 112800 | H7: 112800 | I7: Kredit
B8: JOSSY | C8: 46143.317 | D8: SUMBER BERKAH | E8: FITRI BOTOL 800ML | F8: 1 | G8: 215100 | H8: 215100 | I8: Kredit
B9: JOSSY | C9: 46143.318 | D9: TOKO AL FAZA | E9: FITRI BOTOL 400ML | F9: 1 | G9: 112800 | H9: 112800 | I9: Kredit
B10: JOSSY | C10: 46143.318 | D10: TOKO AL FAZA | E10: FITRI BOTOL 800ML | F10: 2 | G10: 215100 | H10: 430200 | I10: Kredit
B11: JOSSY | C11: 46143.319 | D11: TOKO SEPTI | E11: FITRI BOTOL 800ML | F11: 1 | G11: 215100 | H11: 215100 | I11: Kredit
B12: JOSSY | C12: 46143.319 | D12: TOKO PUAS MART | E12: FITRI BOTOL 400ML | F12: 1 | G12: 112800 | H12: 112800 | I12: Kredit
B13: JOSSY | C13: 46143.319 | D13: TOKO PUAS MART | E13: FITRI BOTOL 800ML | F13: 1 | G13: 215100 | H13: 215100 | I13: Kredit
B14: JOSSY | C14: 46143.32 | D14: BU JOKO 2 | E14: FITRI BOTOL 400ML | F14: 3 | G14: 112800 | H14: 338400 | I14: Cash
B15: JOSSY | C15: 46143.32 | D15: BU JOKO 2 | E15: FITRI BOTOL 800ML | F15: 2 | G15: 215100 | H15: 430200 | I15: Cash
... B354: JOSSY | C354: 46165.314 | D354: TOKO AS-TSABIT | E354: FITRI BOTOL 800ML | F354: 2 | G354: 215100 | H354: 430200 | I354: Kredit
F355: =SUBTOTAL(9,F4:F354) -> 1044 | H355: =SUBTOTAL(9,H4:H354) -> 193671900
D358: CASH | F358: KREDIT / TEMPO | H358: TOTAL
D359: QTY | E359: NOM | F359: QTY | G359: NOM | H359: QTY | I359: NOMINAL
C360: FB200 | D360: 3 | E360: 347400 | G360: 3 | H360: =SUM(D360+F360) -> 3 | I360: =SUM(E360+G360) -> 347403
C361: FB400 | D361: 142 | E361: 16051200 | F361: 152 | G361: 17193600 | H361: =SUM(D361+F361) -> 294 | I361: =SUM(E361+G361) -> 33244800
C362: FB800 | D362: 354 | E362: 75545400 | F362: 393 | G362: 84534300 | H362: =SUM(D362+F362) -> 747 | I362: =SUM(E362+G362) -> 160079700
D364: =SUM(D360:D362) -> 499 | E364: =SUM(E360:E362) -> 91944000 | F364: =SUM(F360:F362) -> 545 | G364: =SUM(G360:G362) -> 101727903 | H364: =SUM(H360:H362) -> 1044 | I364: =SUM(I360:I363) -> 193671903
J365: =SUM(D364+F364) -> 1044 | K365: =SUM(E364+G364) -> 193671903
C367: PROFIT CASH JOSSY
C368: PRODUK | D368: HARGA BELI | E368: QTY TERJUAL CASH | F368: NOM PEMBELIAN | G368: NOMINAL PENJUALAN | H368: PROFIT CASH
C369: FB200 | D369: 110500 | E369: =SUM(D360) -> 3 | F369: =SUM(D369*E369) -> 331500 | G369: =SUM(E360) -> 347400 | I369: =SUM(G369-F369) -> 15900
C370: FB400 | D370: 107500 | E370: =SUM(D361) -> 142 | F370: =SUM(D370*E370) -> 15265000 | G370: =SUM(E361) -> 16051200 | I370: =SUM(G370-F370) -> 786200
C371: FB800 | D371: 201900 | E371: =SUM(D362) -> 354 | F371: =SUM(D371*E371) -> 71472600 | G371: =SUM(E362) -> 75545400 | I371: =SUM(G371-F371) -> 4072800
E372: =SUM(E369:E371) -> 499
I373: =SUM(I369:I371) -> 4874900
C375: PROFIT TEMPO JOSSY
C376: PRODUK | D376: HARGA BELI | E376: QTY TERJUAL TEMPO | F376: NOM PEMBELIAN | G376: NOMINAL PENJUALAN | H376: PROFIT TEMPO
C377: FB200 | D377: 110500 | E377: =SUM(F360) -> 0 | F377: =SUM(D377*E377) -> 0 | G377: =SUM(G360) -> 3 | I377: =SUM(G377-F377) -> 3
C378: FB400 | D378: 107500 | E378: =SUM(F361) -> 152 | F378: =SUM(D378*E378) -> 16340000 | G378: =SUM(G361) -> 17193600 | I378: =SUM(G378-F378) -> 853600
C379: FB800 | D379: 201900 | E379: =SUM(F362) -> 393 | F379: =SUM(D379*E379) -> 79346700 | G379: =SUM(G362) -> 84534300 | I379: =SUM(G379-F379) -> 5187600
E380: =SUM(E377:E379) -> 545
I381: =SUM(I377:I379) -> 6041203

Sheet RAJU
B1: penjualan raju
B3: Sales | C3: Tanggal | D3: Customer | E3: Produk | F3: QTY Penjualan ( krat) | G3: Harga jual | H3: Nominal | I3: Jenis Pembayaran
B4: RAJU | C4: 46144.325 | D4: TOKO SUKRON | E4: FITRI BOTOL 800ML | F4: 5 | G4: 215100 | H4: 1075500 | I4: Cash
B5: RAJU | C5: 46144.325 | D5: TOKO BARU JAYA | E5: FITRI BOTOL 400ML | F5: 5 | G5: 112800 | H5: 564000 | I5: Kredit
B6: RAJU | C6: 46144.326 | D6: TOKO KIOS PATRA | E6: FITRI BOTOL 800ML | F6: 5 | G6: 215100 | H6: 1075500 | I6: Cash
B7: RAJU | C7: 46144.327 | D7: TOKO YINTA | E7: FITRI BOTOL 800ML | F7: 2 | G7: 215100 | H7: 430200 | I7: Kredit
B8: RAJU | C8: 46144.328 | D8: TOKO YANTI | E8: FITRI BOTOL 400ML | F8: 1 | G8: 112800 | H8: 112800 | I8: Cash
B9: RAJU | C9: 46144.328 | D9: TOKO YANTI | E9: FITRI BOTOL 800ML | F9: 1 | G9: 215100 | H9: 215100 | I9: Cash
B10: RAJU | C10: 46144.329 | D10: TOKO SOLEHUDIN | E10: FITRI BOTOL 400ML | F10: 1 | G10: 112800 | H10: 112800 | I10: Cash
B11: RAJU | C11: 46144.329 | D11: TOKO SOLEHUDIN | E11: FITRI BOTOL 800ML | F11: 2 | G11: 215100 | H11: 430200 | I11: Cash
B12: RAJU | C12: 46144.33 | D12: TOKO KURNIA CELL | E12: FITRI BOTOL 400ML | F12: 1 | G12: 112800 | H12: 112800 | I12: Kredit
B13: RAJU | C13: 46144.33 | D13: TOKO KURNIA CELL | E13: FITRI BOTOL 800ML | F13: 1 | G13: 215100 | H13: 215100 | I13: Kredit
B14: RAJU | C14: 46146.33 | D14: TOKO SUMI | E14: FITRI BOTOL 400ML | F14: 1 | G14: 112800 | H14: 112800 | I14: Kredit
B15: RAJU | C15: 46146.33 | D15: TOKO SUMI | E15: FITRI BOTOL 800ML | F15: 1 | G15: 215100 | H15: 215100 | I15: Kredit
... B167: RAJU | C167: 46165.345 | D167: AFFA MART | E167: FITRI BOTOL 800ML | F167: 5 | G167: 215100 | H167: 1075500 | I167: Kredit
F168: =SUBTOTAL(9,F4:F167) -> 381 | H168: =SUBTOTAL(9,H4:H167) -> 81953100
D171: CASH | F171: KREDIT / TEMPO | H171: TOTAL
D172: QTY | E172: NOM | F172: QTY | G172: NOM | H172: QTY | I172: NOMINAL
C173: FB200 | I173: =SUM(E173+G173) -> 0
C174: FB400 | D174: 7 | E174: 792800 | F174: 265 | G174: 30001600 | H174: =SUM(D174+F174) -> 272 | I174: =SUM(E174+G174) -> 30794400
C175: FB800 | D175: 125 | E175: 26287500 | F175: 381 | G175: 81953100 | H175: =SUM(D175+F175) -> 506 | I175: =SUM(E175+G175) -> 108240600
D177: =SUM(D174:D175) -> 132 | E177: =SUM(E173:E175) -> 27080300 | F177: =SUM(F173:F175) -> 646 | G177: =SUM(G173:G175) -> 111954700 | H177: =SUM(H173:H175) -> 778 | I177: =SUM(I173:I176) -> 139035000
J178: =SUM(D177+F177) -> 778
C181: PROFIT CASH RAJU
C182: PRODUK | D182: HARGA BELI | E182: QTY TERJUAL CASH | F182: NOM PEMBELIAN | G182: NOMINAL PENJUALAN | H182: PROFIT CASH
C183: FB200 | D183: 110500 | E183: =SUM(D173) -> 0 | F183: =SUM(D183*E183) -> 0
C184: FB400 | D184: 107500 | E184: =SUM(D174) -> 7 | F184: =SUM(D184*E184) -> 752500 | G184: =SUM(E174) -> 792800 | I184: =SUM(E174-F184) -> 40300
C185: FB800 | D185: 201900 | E185: =SUM(D175) -> 125 | F185: =SUM(D185*E185) -> 25237500 | G185: =SUM(E175) -> 26287500 | I185: =SUM(E175-F185) -> 1050000
I187: =SUM(I183:I185) -> 1090300
C189: PROFIT TEMPO RAJU
C190: PRODUK | D190: HARGA BELI | E190: QTY TERJUAL TEMPO | F190: NOM PEMBELIAN | G190: NOMINAL PENJUALAN | H190: PROFIT TEMPO
C191: FB200 | D191: 110500
C192: FB400 | D192: 107500 | E192: 265 | F192: =SUM(D192*E192) -> 28487500 | G192: =SUM(G174) -> 30001600 | I192: =SUM(G192-F192) -> 1514100
C193: FB800 | D193: 201900 | E193: 381 | F193: =SUM(D193*E193) -> 76923900 | G193: =SUM(G175) -> 81953100 | I193: =SUM(G193-F193) -> 5029200
I195: =SUM(I192:I193) -> 6543300

Sheet HAFID
B1: penjualan hafid
B3: Sales | C3: Tanggal | D3: Customer | E3: Produk | F3: QTY Penjualan ( krat) | G3: Harga jual | H3: Nominal | I3: Jenis Pembayaran
B4: HAFID | C4: 46143.319 | D4: TOKO WIWIN | E4: FITRI BOTOL 800ML | F4: 2 | G4: 215100 | H4: 430200 | I4: Kredit
B5: HAFID | C5: 46143.32 | D5: TOKO BAKSO ANANDA | E5: FITRI BOTOL 800ML | F5: 1 | G5: 215100 | H5: 215100 | I5: Kredit
B6: HAFID | C6: 46143.323 | D6: TOKO SULIS | E6: FITRI BOTOL 400ML | F6: 5 | G6: 112800 | H6: 564000 | I6: Cash
B7: HAFID | C7: 46143.324 | D7: TOKO BU JANNAH | E7: FITRI BOTOL 400ML | F7: 5 | G7: 112800 | H7: 564000 | I7: Cash
B8: HAFID | C8: 46143.324 | D8: TOKO NANANG | E8: FITRI BOTOL 400ML | F8: 2 | G8: 112800 | H8: 225600 | I8: Kredit
B9: HAFID | C9: 46143.325 | D9: TOKO UCOK | E9: FITRI BOTOL 800ML | F9: 5 | G9: 215100 | H9: 1075500 | I9: Cash
B10: HAFID | C10: 46143.326 | D10: TOKO BANON JAYA | E10: FITRI BOTOL 400ML | F10: 2 | G10: 112800 | H10: 225600 | I10: Kredit
B11: HAFID | C11: 46143.326 | D11: TOKO BANON JAYA | E11: FITRI BOTOL 800ML | F11: 3 | G11: 215100 | H11: 645300 | I11: Kredit
B12: HAFID | C12: 46143.328 | D12: TOKO NARTI | E12: FITRI BOTOL 400ML | F12: 2 | G12: 112800 | H12: 225600 | I12: Kredit
B13: HAFID | C13: 46143.333 | D13: TOKO WANDI | E13: FITRI BOTOL 800ML | F13: 1 | G13: 215100 | H13: 215100 | I13: Cash
B14: HAFID | C14: 46144.336 | D14: TOKO LISMA JAYA | E14: FITRI BOTOL 400ML | F14: 1 | G14: 112800 | H14: 112800 | I14: Kredit
B15: HAFID | C15: 46144.336 | D15: TOKO LISMA JAYA | E15: FITRI BOTOL 800ML | F15: 1 | G15: 215100 | H15: 215100 | I15: Kredit
... B300: HAFID | C300: 46165.329 | D300: TOKO DIAN | E300: FITRI BOTOL 800ML | F300: 1 | G300: 215100 | H300: 215100 | I300: Kredit
D304: CASH | F304: KREDIT / TEMPO | H304: TOTAL
D305: QTY | E305: NOM | F305: QTY | G305: NOM | H305: QTY | I305: NOMINAL
C306: FB200
C307: FB400 | D307: 178 | E307: 20153600 | F307: 144 | G307: 16273600 | H307: =SUM(D307+F307) -> 322 | I307: =SUM(E307+G307) -> 36427200
C308: FB800 | D308: 214 | E308: 45731400 | F308: 347 | G308: 74639700 | H308: =SUM(D308+F308) -> 561 | I308: =SUM(E308+G308) -> 120371100
D310: =SUM(D307:D308) -> 392 | E310: =SUM(E306:E308) -> 65885000 | F310: =SUM(F306:F308) -> 491 | G310: =SUM(G306:G308) -> 90913300 | H310: =SUM(H306:H308) -> 883 | I310: =SUM(I306:I309) -> 156798300
C314: PROFIT CAS HAFID
C315: PRODUK | D315: HARGA BELI | E315: QTY TERJUAL CASH | F315: NOM PEMBELIAN | G315: NOMINAL PENJUALAN | H315: PROFIT CASH
C316: FB200 | D316: 110500 | E316: =SUM(D306) -> 0 | F316: =SUM(D316*E316) -> 0
C317: FB400 | D317: 107500 | E317: =SUM(D307) -> 178 | F317: =SUM(D317*E317) -> 19135000 | G317: =SUM(E307) -> 20153600 | I317: =SUM(E307-F317) -> 1018600
C318: FB800 | D318: 201900 | E318: =SUM(D308) -> 214 | F318: =SUM(D318*E318) -> 43206600 | G318: =SUM(E308) -> 45731400 | I318: =SUM(E308-F318) -> 2524800
G320: =SUM(G317:G318) -> 65885000 | I320: =SUM(I317:I318) -> 3543400
C322: PROFIT TEMPO HAFID
C323: PRODUK | D323: HARGA BELI | E323: QTY TERJUAL TEMPO | F323: NOM PEMBELIAN | G323: NOMINAL PENJUALAN | H323: PROFIT TEMPO
C324: FB200 | D324: 110500
C325: FB400 | D325: 107500 | E325: =SUM(F307) -> 144 | F325: =SUM(D325*E325) -> 15480000 | G325: =SUM(G307) -> 16273600 | I325: =SUM(G325-F325) -> 793600
C326: FB800 | D326: 201900 | E326: =SUM(F308) -> 347 | F326: =SUM(D326*E326) -> 70059300 | G326: =SUM(G308) -> 74639700 | I326: =SUM(G326-F326) -> 4580400
I328: =SUM(I325:I326) -> 5374000
